sample/__init__.py
sample/package_data.dat
sample/simple.py
gdpr-1.0.0.dist-info/LICENSE.txt
gdpr-1.0.0.dist-info/METADATA
gdpr-1.0.0.dist-info/WHEEL
gdpr-1.0.0.dist-info/entry_points.txt
gdpr-1.0.0.dist-info/top_level.txt
gdpr-1.0.0.dist-info/RECORD
