Metadata-Version: 2.1
Name: gdpr
Version: 1.0.0
Summary: Tutorial project 'Publish to PyPI, and let's see how the *Python Software Foundation* interprets consent GDPR-wise'
License: Copyright (c) 2016 The Python Packaging Authority (PyPA)
Project-URL: Homepage, https://github.com/Abdull/gdpr
Project-URL: Bug Reports, https://github.com/Abdull/gdpr/issues
Project-URL: Source, https://github.com/Abdull/gdpr
Keywords: sample,gdpr,pypi,psf,pip,pii,privacy
Classifier: Development Status :: 5 - Production/Stable
Classifier: Intended Audience :: Legal Industry
Classifier: Topic :: Education
Classifier: Topic :: Other/Nonlisted Topic
Classifier: Topic :: System :: Software Distribution
Classifier: License :: OSI Approved :: MIT License
Classifier: Programming Language :: Python :: 3
Classifier: Programming Language :: Python :: 3.7
Classifier: Programming Language :: Python :: 3.8
Classifier: Programming Language :: Python :: 3.9
Classifier: Programming Language :: Python :: 3.10
Classifier: Programming Language :: Python :: 3.11
Classifier: Programming Language :: Python :: 3 :: Only
Requires-Python: >=3.7
License-File: LICENSE.txt
